polyglot/__init__.py
polyglot/__main__.py
polyglot/arguments.py
polyglot/commands.py
polyglot/connectors.py
polyglot/errors.py
polyglot/handlers.py
polyglot/license.py
polyglot/polyglot.py
polyglot/translators.py
polyglot/utils.py
polyglot_translator-2.2.4.dist-info/LICENSE
polyglot_translator-2.2.4.dist-info/METADATA
polyglot_translator-2.2.4.dist-info/WHEEL
polyglot_translator-2.2.4.dist-info/entry_points.txt
polyglot_translator-2.2.4.dist-info/top_level.txt
polyglot_translator-2.2.4.dist-info/RECORD
