Metadata-Version: 2.1
Name: polyglot-translator
Version: 2.2.4
Summary: Automation CLI tool that, using the DeepL API, generates a JSON or a PO file from a given source file.
Home-page: https://github.com/riccardoFasan/polyglot
Author: Riccardo Fasan
Author-email: fasanriccardo21@gmail.com
License: MIT
Project-URL: BugTracker, https://github.com/riccardoFasan/polyglot/issues
Project-URL: Homepage, https://github.com/riccardoFasan/polyglot
Classifier: Programming Language :: Python :: 3.10
Classifier: License :: OSI Approved :: MIT License
Classifier: Operating System :: OS Independent
Requires-Python: >=3.8
License-File: LICENSE
Requires-Dist: requests
Requires-Dist: colorama
Requires-Dist: polib
Requires-Dist: progressbar2
Requires-Dist: deepl
